test/__init__.py
test/fakes.py
test/test_main.py
test/test_yum_config.py
tripleo_yum_config/__init__.py
tripleo_yum_config/__main__.py
tripleo_yum_config/constants.py
tripleo_yum_config/exceptions.py
tripleo_yum_config/yum_config.py
tripleo_yum_config-0.1.1.dev39.data/data/share/ansible/plugins/modules/tripleo_yum_config.py
tripleo_yum_config-0.1.1.dev39.dist-info/LICENSE
tripleo_yum_config-0.1.1.dev39.dist-info/METADATA
tripleo_yum_config-0.1.1.dev39.dist-info/WHEEL
tripleo_yum_config-0.1.1.dev39.dist-info/entry_points.txt
tripleo_yum_config-0.1.1.dev39.dist-info/pbr.json
tripleo_yum_config-0.1.1.dev39.dist-info/top_level.txt
tripleo_yum_config-0.1.1.dev39.dist-info/RECORD
